{
  "manifestVersion": "1.11",
  "id": "aaa23c9b-a199-4501-ade7-fcd62974b3af",
  "version": "1.0.2",
  "name": "Ramco CHIA",
  "accentColor": "#FFFFFF",
  "amsSellerAccountId": 67648410,
  "appMetadata": {},
  "bots": [
    {
      "allowBotMessageDeleteByUser": false,
      "commandLists": [
        {
          "commands": [
            {
              "description": "Get Help Items (Shows what bot can do)",
              "title": "Help"
            },
            {
              "description": "Cancel / abort /quit the current transactions and starts a new thread",
              "title": "Exit"
            },
            {
              "description": "Fetches available leave balance",
              "title": "What is my leave balance"
            },
            {
              "description": "To get your payslip by email as attachment",
              "title": "email my payslip"
            },
            {
              "description": "To apply annual leave for today",
              "title": "Apply annual leave for today"
            },
            {
              "description": "shows my recent claims / expense information",
              "title": "show my recent claims"
            },
            {
              "description": "Shows 360 degree snapshot of an employee",
              "title": "Employee Snapshot"
            },
            {
              "description": "Shows the holidays list for the current year",
              "title": "Show my Holidays list"
            },
            {
              "description": "To view team members information",
              "title": "Team view"
            }
          ],
          "scopes": [
            "personal"
          ]
        }
      ],
      "id": "6fc1ba62-4e90-4cb5-ac04-dbdb37605308",
      "isNotificationOnly": false,
      "scopes": [
        "personal"
      ],
      "supportsCalling": false,
      "supportsFiles": true,
      "supportsVideo": false
    }
  ],
  "categories": [
    "HumanResourcesAndRecruiting"
  ],
  "creatorId": "",
  "defaultBlockUntilAdminAction": false,
  "developerName": "Ramco Systems",
  "developerUrl": "https://www.ramco.com/chatbot",
  "industries": [
    "Finance",
    "ProfessionalServices"
  ],
  "isBlockable": true,
  "isCoreApp": false,
  "isFullScreen": false,
  "isFullTrust": false,
  "isMetaOSApp": false,
  "isPinnable": true,
  "isPreinstallable": true,
  "isTeamsOwned": false,
  "isTenantConfigurable": true,
  "keywords": [
    "ramco chia, ramco, chia"
  ],
  "largeImageUrl": "https://res.cdn.office.net/teamsappdata/ais_prod_v1/evergreen-assets/aaa23c9b-a199-4501-ade7-fcd62974b3af/2025071112210643/aaa23c9b-a199-4501-ade7-fcd62974b3af_largeimage.png",
  "lastUpdatedAt": "2022-01-05T03:56:05.4378014+00:00",
  "longDescription": "Let's face it. There are several things to take care of at work. Won't it be nice to have a personal assistant who can be of help? Be it time off, expenses, travel, pay, calendar, purchase, stock and everything in self-service with loads of convenience, just chat with me.\nThis app is available only for employees of large enterprises. Please connect with Ramco Systems at contact@ramco.com if you / your organization is interested to use RamcoCHIA.",
  "mpnId": "4950732",
  "officeAssetId": "WA200000987",
  "permissions": [
    "Identity",
    "MessageTeamMembers"
  ],
  "privacyUrl": "https://www.ramco.com/chatbot/privacy-policy/",
  "screenshotUrls": [
    "https://res.cdn.office.net/teamsappdata/ais_prod_v1/evergreen-assets/aaa23c9b-a199-4501-ade7-fcd62974b3af/2025071112210643/aaa23c9b-a199-4501-ade7-fcd62974b3af_screenshot/0.jpeg",
    "https://res.cdn.office.net/teamsappdata/ais_prod_v1/evergreen-assets/aaa23c9b-a199-4501-ade7-fcd62974b3af/2025071112210643/aaa23c9b-a199-4501-ade7-fcd62974b3af_screenshot/1.jpeg"
  ],
  "securityComplianceInfo": {
    "status": "unattested"
  },
  "shortDescription": "I am Chia, your virtual assistant @work to help you on the go!",
  "showLoadingIndicator": false,
  "smallImageUrl": "https://res.cdn.office.net/teamsappdata/ais_prod_v1/evergreen-assets/aaa23c9b-a199-4501-ade7-fcd62974b3af/2025071112210643/aaa23c9b-a199-4501-ade7-fcd62974b3af_smallimage.png",
  "staticTabs": [
    {
      "entityId": "conversations",
      "scopes": [
        "personal"
      ]
    },
    {
      "entityId": "about",
      "scopes": [
        "personal"
      ]
    }
  ],
  "systemVersion": "2025071112210643",
  "termsOfUseUrl": "https://www.ramco.com/chatbot/terms-and-conditions",
  "validDomains": [
    "*.ramco.com"
  ],
  "publishingPolicy": {
    "isFlaggedForViolations": false,
    "releaseType": "standard",
    "audienceConfiguration": {
      "allowedCountryAudience": {
        "countrySelectionMode": "specificCountries",
        "specificCountryAudiences": [
          {
            "countryCode": "AD",
            "stateAudienceSelectionMode": "allStates"
          },
          {
            "countryCode": "AE",
            "stateAudienceSelectionMode": "allStates"
          },
          {
            "countryCode": "AF",
            "stateAudienceSelectionMode": "allStates"
          },
          {
            "countryCode": "AG",
            "stateAudienceSelectionMode": "allStates"
          },
          {
            "countryCode": "AI",
            "stateAudienceSelectionMode": "allStates"
          },
          {
            "countryCode": "AL",
            "stateAudienceSelectionMode": "allStates"
          },
          {
            "countryCode": "AM",
            "stateAudienceSelectionMode": "allStates"
          },
          {
            "countryCode": "AO",
            "stateAudienceSelectionMode": "allStates"
          },
          {
            "countryCode": "AQ",
            "stateAudienceSelectionMode": "allStates"
          },
          {
            "countryCode": "AR",
            "stateAudienceSelectionMode": "allStates"
          },
          {
            "countryCode": "AS",
            "stateAudienceSelectionMode": "allStates"
          },
          {
            "countryCode": "AT",
            "stateAudienceSelectionMode": "allStates"
          },
          {
            "countryCode": "AU",
            "stateAudienceSelectionMode": "allStates"
          },
          {
            "countryCode": "AW",
            "stateAudienceSelectionMode": "allStates"
          },
          {
            "countryCode": "AX",
            "stateAudienceSelectionMode": "allStates"
          },
          {
            "countryCode": "AZ",
            "stateAudienceSelectionMode": "allStates"
          },
          {
            "countryCode": "BA",
            "stateAudienceSelectionMode": "allStates"
          },
          {
            "countryCode": "BB",
            "stateAudienceSelectionMode": "allStates"
          },
          {
            "countryCode": "BD",
            "stateAudienceSelectionMode": "allStates"
          },
          {
            "countryCode": "BE",
            "stateAudienceSelectionMode": "allStates"
          },
          {
            "countryCode": "BF",
            "stateAudienceSelectionMode": "allStates"
          },
          {
            "countryCode": "BG",
            "stateAudienceSelectionMode": "allStates"
          },
          {
            "countryCode": "BH",
            "stateAudienceSelectionMode": "allStates"
          },
          {
            "countryCode": "BI",
            "stateAudienceSelectionMode": "allStates"
          },
          {
            "countryCode": "BJ",
            "stateAudienceSelectionMode": "allStates"
          },
          {
            "countryCode": "BL",
            "stateAudienceSelectionMode": "allStates"
          },
          {
            "countryCode": "BM",
            "stateAudienceSelectionMode": "allStates"
          },
          {
            "countryCode": "BN",
            "stateAudienceSelectionMode": "allStates"
          },
          {
            "countryCode": "BO",
            "stateAudienceSelectionMode": "allStates"
          },
          {
            "countryCode": "BQ",
            "stateAudienceSelectionMode": "allStates"
          },
          {
            "countryCode": "BR",
            "stateAudienceSelectionMode": "allStates"
          },
          {
            "countryCode": "BS",
            "stateAudienceSelectionMode": "allStates"
          },
          {
            "countryCode": "BT",
            "stateAudienceSelectionMode": "allStates"
          },
          {
            "countryCode": "BV",
            "stateAudienceSelectionMode": "allStates"
          },
          {
            "countryCode": "BW",
            "stateAudienceSelectionMode": "allStates"
          },
          {
            "countryCode": "BY",
            "stateAudienceSelectionMode": "allStates"
          },
          {
            "countryCode": "BZ",
            "stateAudienceSelectionMode": "allStates"
          },
          {
            "countryCode": "CA",
            "stateAudienceSelectionMode": "allStates"
          },
          {
            "countryCode": "CC",
            "stateAudienceSelectionMode": "allStates"
          },
          {
            "countryCode": "CD",
            "stateAudienceSelectionMode": "allStates"
          },
          {
            "countryCode": "CF",
            "stateAudienceSelectionMode": "allStates"
          },
          {
            "countryCode": "CG",
            "stateAudienceSelectionMode": "allStates"
          },
          {
            "countryCode": "CH",
            "stateAudienceSelectionMode": "allStates"
          },
          {
            "countryCode": "CI",
            "stateAudienceSelectionMode": "allStates"
          },
          {
            "countryCode": "CK",
            "stateAudienceSelectionMode": "allStates"
          },
          {
            "countryCode": "CL",
            "stateAudienceSelectionMode": "allStates"
          },
          {
            "countryCode": "CM",
            "stateAudienceSelectionMode": "allStates"
          },
          {
            "countryCode": "CN",
            "stateAudienceSelectionMode": "allStates"
          },
          {
            "countryCode": "CO",
            "stateAudienceSelectionMode": "allStates"
          },
          {
            "countryCode": "CR",
            "stateAudienceSelectionMode": "allStates"
          },
          {
            "countryCode": "CV",
            "stateAudienceSelectionMode": "allStates"
          },
          {
            "countryCode": "CW",
            "stateAudienceSelectionMode": "allStates"
          },
          {
            "countryCode": "CX",
            "stateAudienceSelectionMode": "allStates"
          },
          {
            "countryCode": "CY",
            "stateAudienceSelectionMode": "allStates"
          },
          {
            "countryCode": "CZ",
            "stateAudienceSelectionMode": "allStates"
          },
          {
            "countryCode": "DE",
            "stateAudienceSelectionMode": "allStates"
          },
          {
            "countryCode": "DJ",
            "stateAudienceSelectionMode": "allStates"
          },
          {
            "countryCode": "DK",
            "stateAudienceSelectionMode": "allStates"
          },
          {
            "countryCode": "DM",
            "stateAudienceSelectionMode": "allStates"
          },
          {
            "countryCode": "DO",
            "stateAudienceSelectionMode": "allStates"
          },
          {
            "countryCode": "DZ",
            "stateAudienceSelectionMode": "allStates"
          },
          {
            "countryCode": "EC",
            "stateAudienceSelectionMode": "allStates"
          },
          {
            "countryCode": "EE",
            "stateAudienceSelectionMode": "allStates"
          },
          {
            "countryCode": "EG",
            "stateAudienceSelectionMode": "allStates"
          },
          {
            "countryCode": "ER",
            "stateAudienceSelectionMode": "allStates"
          },
          {
            "countryCode": "ES",
            "stateAudienceSelectionMode": "allStates"
          },
          {
            "countryCode": "ET",
            "stateAudienceSelectionMode": "allStates"
          },
          {
            "countryCode": "FI",
            "stateAudienceSelectionMode": "allStates"
          },
          {
            "countryCode": "FJ",
            "stateAudienceSelectionMode": "allStates"
          },
          {
            "countryCode": "FK",
            "stateAudienceSelectionMode": "allStates"
          },
          {
            "countryCode": "FM",
            "stateAudienceSelectionMode": "allStates"
          },
          {
            "countryCode": "FO",
            "stateAudienceSelectionMode": "allStates"
          },
          {
            "countryCode": "FR",
            "stateAudienceSelectionMode": "allStates"
          },
          {
            "countryCode": "GA",
            "stateAudienceSelectionMode": "allStates"
          },
          {
            "countryCode": "GB",
            "stateAudienceSelectionMode": "allStates"
          },
          {
            "countryCode": "GD",
            "stateAudienceSelectionMode": "allStates"
          },
          {
            "countryCode": "GE",
            "stateAudienceSelectionMode": "allStates"
          },
          {
            "countryCode": "GF",
            "stateAudienceSelectionMode": "allStates"
          },
          {
            "countryCode": "GG",
            "stateAudienceSelectionMode": "allStates"
          },
          {
            "countryCode": "GH",
            "stateAudienceSelectionMode": "allStates"
          },
          {
            "countryCode": "GI",
            "stateAudienceSelectionMode": "allStates"
          },
          {
            "countryCode": "GL",
            "stateAudienceSelectionMode": "allStates"
          },
          {
            "countryCode": "GM",
            "stateAudienceSelectionMode": "allStates"
          },
          {
            "countryCode": "GN",
            "stateAudienceSelectionMode": "allStates"
          },
          {
            "countryCode": "GP",
            "stateAudienceSelectionMode": "allStates"
          },
          {
            "countryCode": "GQ",
            "stateAudienceSelectionMode": "allStates"
          },
          {
            "countryCode": "GR",
            "stateAudienceSelectionMode": "allStates"
          },
          {
            "countryCode": "GS",
            "stateAudienceSelectionMode": "allStates"
          },
          {
            "countryCode": "GT",
            "stateAudienceSelectionMode": "allStates"
          },
          {
            "countryCode": "GU",
            "stateAudienceSelectionMode": "allStates"
          },
          {
            "countryCode": "GW",
            "stateAudienceSelectionMode": "allStates"
          },
          {
            "countryCode": "GY",
            "stateAudienceSelectionMode": "allStates"
          },
          {
            "countryCode": "HK",
            "stateAudienceSelectionMode": "allStates"
          },
          {
            "countryCode": "HM",
            "stateAudienceSelectionMode": "allStates"
          },
          {
            "countryCode": "HN",
            "stateAudienceSelectionMode": "allStates"
          },
          {
            "countryCode": "HR",
            "stateAudienceSelectionMode": "allStates"
          },
          {
            "countryCode": "HT",
            "stateAudienceSelectionMode": "allStates"
          },
          {
            "countryCode": "HU",
            "stateAudienceSelectionMode": "allStates"
          },
          {
            "countryCode": "ID",
            "stateAudienceSelectionMode": "allStates"
          },
          {
            "countryCode": "IE",
            "stateAudienceSelectionMode": "allStates"
          },
          {
            "countryCode": "IL",
            "stateAudienceSelectionMode": "allStates"
          },
          {
            "countryCode": "IM",
            "stateAudienceSelectionMode": "allStates"
          },
          {
            "countryCode": "IN",
            "stateAudienceSelectionMode": "allStates"
          },
          {
            "countryCode": "IO",
            "stateAudienceSelectionMode": "allStates"
          },
          {
            "countryCode": "IQ",
            "stateAudienceSelectionMode": "allStates"
          },
          {
            "countryCode": "IS",
            "stateAudienceSelectionMode": "allStates"
          },
          {
            "countryCode": "IT",
            "stateAudienceSelectionMode": "allStates"
          },
          {
            "countryCode": "JE",
            "stateAudienceSelectionMode": "allStates"
          },
          {
            "countryCode": "JM",
            "stateAudienceSelectionMode": "allStates"
          },
          {
            "countryCode": "JO",
            "stateAudienceSelectionMode": "allStates"
          },
          {
            "countryCode": "JP",
            "stateAudienceSelectionMode": "allStates"
          },
          {
            "countryCode": "KE",
            "stateAudienceSelectionMode": "allStates"
          },
          {
            "countryCode": "KG",
            "stateAudienceSelectionMode": "allStates"
          },
          {
            "countryCode": "KH",
            "stateAudienceSelectionMode": "allStates"
          },
          {
            "countryCode": "KI",
            "stateAudienceSelectionMode": "allStates"
          },
          {
            "countryCode": "KM",
            "stateAudienceSelectionMode": "allStates"
          },
          {
            "countryCode": "KN",
            "stateAudienceSelectionMode": "allStates"
          },
          {
            "countryCode": "KR",
            "stateAudienceSelectionMode": "allStates"
          },
          {
            "countryCode": "KW",
            "stateAudienceSelectionMode": "allStates"
          },
          {
            "countryCode": "KY",
            "stateAudienceSelectionMode": "allStates"
          },
          {
            "countryCode": "KZ",
            "stateAudienceSelectionMode": "allStates"
          },
          {
            "countryCode": "LA",
            "stateAudienceSelectionMode": "allStates"
          },
          {
            "countryCode": "LB",
            "stateAudienceSelectionMode": "allStates"
          },
          {
            "countryCode": "LC",
            "stateAudienceSelectionMode": "allStates"
          },
          {
            "countryCode": "LI",
            "stateAudienceSelectionMode": "allStates"
          },
          {
            "countryCode": "LK",
            "stateAudienceSelectionMode": "allStates"
          },
          {
            "countryCode": "LR",
            "stateAudienceSelectionMode": "allStates"
          },
          {
            "countryCode": "LS",
            "stateAudienceSelectionMode": "allStates"
          },
          {
            "countryCode": "LT",
            "stateAudienceSelectionMode": "allStates"
          },
          {
            "countryCode": "LU",
            "stateAudienceSelectionMode": "allStates"
          },
          {
            "countryCode": "LV",
            "stateAudienceSelectionMode": "allStates"
          },
          {
            "countryCode": "LY",
            "stateAudienceSelectionMode": "allStates"
          },
          {
            "countryCode": "MA",
            "stateAudienceSelectionMode": "allStates"
          },
          {
            "countryCode": "MC",
            "stateAudienceSelectionMode": "allStates"
          },
          {
            "countryCode": "MD",
            "stateAudienceSelectionMode": "allStates"
          },
          {
            "countryCode": "ME",
            "stateAudienceSelectionMode": "allStates"
          },
          {
            "countryCode": "MF",
            "stateAudienceSelectionMode": "allStates"
          },
          {
            "countryCode": "MG",
            "stateAudienceSelectionMode": "allStates"
          },
          {
            "countryCode": "MH",
            "stateAudienceSelectionMode": "allStates"
          },
          {
            "countryCode": "MK",
            "stateAudienceSelectionMode": "allStates"
          },
          {
            "countryCode": "ML",
            "stateAudienceSelectionMode": "allStates"
          },
          {
            "countryCode": "MM",
            "stateAudienceSelectionMode": "allStates"
          },
          {
            "countryCode": "MN",
            "stateAudienceSelectionMode": "allStates"
          },
          {
            "countryCode": "MO",
            "stateAudienceSelectionMode": "allStates"
          },
          {
            "countryCode": "MP",
            "stateAudienceSelectionMode": "allStates"
          },
          {
            "countryCode": "MQ",
            "stateAudienceSelectionMode": "allStates"
          },
          {
            "countryCode": "MR",
            "stateAudienceSelectionMode": "allStates"
          },
          {
            "countryCode": "MS",
            "stateAudienceSelectionMode": "allStates"
          },
          {
            "countryCode": "MT",
            "stateAudienceSelectionMode": "allStates"
          },
          {
            "countryCode": "MU",
            "stateAudienceSelectionMode": "allStates"
          },
          {
            "countryCode": "MV",
            "stateAudienceSelectionMode": "allStates"
          },
          {
            "countryCode": "MW",
            "stateAudienceSelectionMode": "allStates"
          },
          {
            "countryCode": "MX",
            "stateAudienceSelectionMode": "allStates"
          },
          {
            "countryCode": "MY",
            "stateAudienceSelectionMode": "allStates"
          },
          {
            "countryCode": "MZ",
            "stateAudienceSelectionMode": "allStates"
          },
          {
            "countryCode": "NA",
            "stateAudienceSelectionMode": "allStates"
          },
          {
            "countryCode": "NC",
            "stateAudienceSelectionMode": "allStates"
          },
          {
            "countryCode": "NE",
            "stateAudienceSelectionMode": "allStates"
          },
          {
            "countryCode": "NF",
            "stateAudienceSelectionMode": "allStates"
          },
          {
            "countryCode": "NG",
            "stateAudienceSelectionMode": "allStates"
          },
          {
            "countryCode": "NI",
            "stateAudienceSelectionMode": "allStates"
          },
          {
            "countryCode": "NL",
            "stateAudienceSelectionMode": "allStates"
          },
          {
            "countryCode": "NO",
            "stateAudienceSelectionMode": "allStates"
          },
          {
            "countryCode": "NP",
            "stateAudienceSelectionMode": "allStates"
          },
          {
            "countryCode": "NR",
            "stateAudienceSelectionMode": "allStates"
          },
          {
            "countryCode": "NU",
            "stateAudienceSelectionMode": "allStates"
          },
          {
            "countryCode": "NZ",
            "stateAudienceSelectionMode": "allStates"
          },
          {
            "countryCode": "OM",
            "stateAudienceSelectionMode": "allStates"
          },
          {
            "countryCode": "PA",
            "stateAudienceSelectionMode": "allStates"
          },
          {
            "countryCode": "PE",
            "stateAudienceSelectionMode": "allStates"
          },
          {
            "countryCode": "PF",
            "stateAudienceSelectionMode": "allStates"
          },
          {
            "countryCode": "PG",
            "stateAudienceSelectionMode": "allStates"
          },
          {
            "countryCode": "PH",
            "stateAudienceSelectionMode": "allStates"
          },
          {
            "countryCode": "PK",
            "stateAudienceSelectionMode": "allStates"
          },
          {
            "countryCode": "PL",
            "stateAudienceSelectionMode": "allStates"
          },
          {
            "countryCode": "PM",
            "stateAudienceSelectionMode": "allStates"
          },
          {
            "countryCode": "PN",
            "stateAudienceSelectionMode": "allStates"
          },
          {
            "countryCode": "PR",
            "stateAudienceSelectionMode": "allStates"
          },
          {
            "countryCode": "PS",
            "stateAudienceSelectionMode": "allStates"
          },
          {
            "countryCode": "PT",
            "stateAudienceSelectionMode": "allStates"
          },
          {
            "countryCode": "PW",
            "stateAudienceSelectionMode": "allStates"
          },
          {
            "countryCode": "PY",
            "stateAudienceSelectionMode": "allStates"
          },
          {
            "countryCode": "QA",
            "stateAudienceSelectionMode": "allStates"
          },
          {
            "countryCode": "RE",
            "stateAudienceSelectionMode": "allStates"
          },
          {
            "countryCode": "RO",
            "stateAudienceSelectionMode": "allStates"
          },
          {
            "countryCode": "RS",
            "stateAudienceSelectionMode": "allStates"
          },
          {
            "countryCode": "RU",
            "stateAudienceSelectionMode": "allStates"
          },
          {
            "countryCode": "RW",
            "stateAudienceSelectionMode": "allStates"
          },
          {
            "countryCode": "SA",
            "stateAudienceSelectionMode": "allStates"
          },
          {
            "countryCode": "SB",
            "stateAudienceSelectionMode": "allStates"
          },
          {
            "countryCode": "SC",
            "stateAudienceSelectionMode": "allStates"
          },
          {
            "countryCode": "SE",
            "stateAudienceSelectionMode": "allStates"
          },
          {
            "countryCode": "SG",
            "stateAudienceSelectionMode": "allStates"
          },
          {
            "countryCode": "SH",
            "stateAudienceSelectionMode": "allStates"
          },
          {
            "countryCode": "SI",
            "stateAudienceSelectionMode": "allStates"
          },
          {
            "countryCode": "SJ",
            "stateAudienceSelectionMode": "allStates"
          },
          {
            "countryCode": "SK",
            "stateAudienceSelectionMode": "allStates"
          },
          {
            "countryCode": "SL",
            "stateAudienceSelectionMode": "allStates"
          },
          {
            "countryCode": "SM",
            "stateAudienceSelectionMode": "allStates"
          },
          {
            "countryCode": "SN",
            "stateAudienceSelectionMode": "allStates"
          },
          {
            "countryCode": "SO",
            "stateAudienceSelectionMode": "allStates"
          },
          {
            "countryCode": "SR",
            "stateAudienceSelectionMode": "allStates"
          },
          {
            "countryCode": "ST",
            "stateAudienceSelectionMode": "allStates"
          },
          {
            "countryCode": "SV",
            "stateAudienceSelectionMode": "allStates"
          },
          {
            "countryCode": "SX",
            "stateAudienceSelectionMode": "allStates"
          },
          {
            "countryCode": "SZ",
            "stateAudienceSelectionMode": "allStates"
          },
          {
            "countryCode": "TC",
            "stateAudienceSelectionMode": "allStates"
          },
          {
            "countryCode": "TD",
            "stateAudienceSelectionMode": "allStates"
          },
          {
            "countryCode": "TF",
            "stateAudienceSelectionMode": "allStates"
          },
          {
            "countryCode": "TG",
            "stateAudienceSelectionMode": "allStates"
          },
          {
            "countryCode": "TH",
            "stateAudienceSelectionMode": "allStates"
          },
          {
            "countryCode": "TJ",
            "stateAudienceSelectionMode": "allStates"
          },
          {
            "countryCode": "TK",
            "stateAudienceSelectionMode": "allStates"
          },
          {
            "countryCode": "TL",
            "stateAudienceSelectionMode": "allStates"
          },
          {
            "countryCode": "TM",
            "stateAudienceSelectionMode": "allStates"
          },
          {
            "countryCode": "TN",
            "stateAudienceSelectionMode": "allStates"
          },
          {
            "countryCode": "TO",
            "stateAudienceSelectionMode": "allStates"
          },
          {
            "countryCode": "TR",
            "stateAudienceSelectionMode": "allStates"
          },
          {
            "countryCode": "TT",
            "stateAudienceSelectionMode": "allStates"
          },
          {
            "countryCode": "TV",
            "stateAudienceSelectionMode": "allStates"
          },
          {
            "countryCode": "TW",
            "stateAudienceSelectionMode": "allStates"
          },
          {
            "countryCode": "TZ",
            "stateAudienceSelectionMode": "allStates"
          },
          {
            "countryCode": "UA",
            "stateAudienceSelectionMode": "allStates"
          },
          {
            "countryCode": "UG",
            "stateAudienceSelectionMode": "allStates"
          },
          {
            "countryCode": "UM",
            "stateAudienceSelectionMode": "allStates"
          },
          {
            "countryCode": "US",
            "stateAudienceSelectionMode": "allStates"
          },
          {
            "countryCode": "UY",
            "stateAudienceSelectionMode": "allStates"
          },
          {
            "countryCode": "UZ",
            "stateAudienceSelectionMode": "allStates"
          },
          {
            "countryCode": "VA",
            "stateAudienceSelectionMode": "allStates"
          },
          {
            "countryCode": "VC",
            "stateAudienceSelectionMode": "allStates"
          },
          {
            "countryCode": "VE",
            "stateAudienceSelectionMode": "allStates"
          },
          {
            "countryCode": "VG",
            "stateAudienceSelectionMode": "allStates"
          },
          {
            "countryCode": "VI",
            "stateAudienceSelectionMode": "allStates"
          },
          {
            "countryCode": "VN",
            "stateAudienceSelectionMode": "allStates"
          },
          {
            "countryCode": "VU",
            "stateAudienceSelectionMode": "allStates"
          },
          {
            "countryCode": "WF",
            "stateAudienceSelectionMode": "allStates"
          },
          {
            "countryCode": "WS",
            "stateAudienceSelectionMode": "allStates"
          },
          {
            "countryCode": "YE",
            "stateAudienceSelectionMode": "allStates"
          },
          {
            "countryCode": "YT",
            "stateAudienceSelectionMode": "allStates"
          },
          {
            "countryCode": "ZA",
            "stateAudienceSelectionMode": "allStates"
          },
          {
            "countryCode": "ZM",
            "stateAudienceSelectionMode": "allStates"
          },
          {
            "countryCode": "ZW",
            "stateAudienceSelectionMode": "allStates"
          }
        ]
      }
    }
  },
  "localizedDefinitions": [],
  "examplePrompts": [
    {
      "prompt": "@Ramco CHIA What is my leave balance?",
      "description": "User asks the bot to show their current leave balance.",
      "command": "What is my leave balance"
    },
    {
      "prompt": "@Ramco CHIA Apply annual leave for today",
      "description": "User instructs the bot to apply for annual leave for the current day.",
      "command": "Apply annual leave for today"
    },
    {
      "prompt": "@Ramco CHIA email my payslip",
      "description": "User requests the bot to send their payslip to their email.",
      "command": "email my payslip"
    }
  ]
}